pysi_cc/__init__.py
pysi_cc/eval_cc.py
pysi_cc/evaluate.py
pysi_cc/forward_integration.py
pysi_cc/print_cc.py
pysi_cc/train.py
pysi_cc/train_hybrid.py
pysi_cc/train_old.py
pysi_cc-0.0.1.dist-info/licenses/LICENSE
pysi_cc-0.0.1.dist-info/METADATA
pysi_cc-0.0.1.dist-info/WHEEL
pysi_cc-0.0.1.dist-info/top_level.txt
pysi_cc-0.0.1.dist-info/RECORD
