Metadata-Version: 2.4
Name: pysi_cc
Version: 0.0.1
Summary: Library to train and use NN models for physical systems
Author: Federico J. Gonzalez
Requires-Python: >=3.7
License-File: LICENSE
Requires-Dist: torch
Requires-Dist: numpy
Dynamic: author
Dynamic: license-file
Dynamic: requires-dist
Dynamic: requires-python
Dynamic: summary
